src/__init__.py
src/app.py
src/writefile_app.py
Flask_App_Install-1.2.dist-info/LICENCE
Flask_App_Install-1.2.dist-info/METADATA
Flask_App_Install-1.2.dist-info/WHEEL
Flask_App_Install-1.2.dist-info/top_level.txt
Flask_App_Install-1.2.dist-info/RECORD
